ibgateway_api_client/__init__.py
ibgateway_api_client/k3s_live_client.py
ibgateway_api_client/k3s_paper_client.py
ibgateway_api_client/test_connection.py
ibgateway_api_client-0.1.1.dist-info/licenses/LICENSE
ibgateway_api_client-0.1.1.dist-info/METADATA
ibgateway_api_client-0.1.1.dist-info/WHEEL
ibgateway_api_client-0.1.1.dist-info/entry_points.txt
ibgateway_api_client-0.1.1.dist-info/top_level.txt
ibgateway_api_client-0.1.1.dist-info/RECORD
