Metadata-Version: 2.4
Name: ibgateway-api-client
Version: 0.1.1
Summary: Python client library for Interactive Brokers Gateway running in Kubernetes (K3s) environments
Home-page: https://github.com/logycon/ibgateway-api-client
Author: Logycon
Author-email: Logycon <dev@logycon.com>
License: MIT
Project-URL: Homepage, https://github.com/logycon/ibgateway-api-client
Project-URL: Documentation, https://github.com/logycon/ibgateway-api-client#readme
Project-URL: Repository, https://github.com/logycon/ibgateway-api-client
Project-URL: Issues, https://github.com/logycon/ibgateway-api-client/issues
Keywords: interactive-brokers,trading,api,kubernetes,k3s,ib-gateway
Classifier: Development Status :: 3 - Alpha
Classifier: Intended Audience :: Financial and Insurance Industry
Classifier: License :: OSI Approved :: MIT License
Classifier: Programming Language :: Python :: 3
Classifier: Programming Language :: Python :: 3.8
Classifier: Programming Language :: Python :: 3.9
Classifier: Programming Language :: Python :: 3.10
Classifier: Programming Language :: Python :: 3.11
Classifier: Programming Language :: Python :: 3.12
Classifier: Topic :: Office/Business :: Financial :: Investment
Classifier: Topic :: Software Development :: Libraries :: Python Modules
Requires-Python: >=3.8
License-File: LICENSE
Requires-Dist: ib-insync>=0.9.86
Requires-Dist: python-dotenv>=1.0.0
Provides-Extra: dev
Requires-Dist: pytest>=7.0; extra == "dev"
Requires-Dist: pytest-asyncio>=0.21.0; extra == "dev"
Requires-Dist: black>=22.0; extra == "dev"
Requires-Dist: flake8>=5.0; extra == "dev"
Requires-Dist: mypy>=1.0; extra == "dev"
Dynamic: author
Dynamic: home-page
Dynamic: license-file
Dynamic: requires-python
